code_secret/__init__.py
code_secret_DARKSHLOSER-0.0.1.dist-info/LICENSE
code_secret_DARKSHLOSER-0.0.1.dist-info/METADATA
code_secret_DARKSHLOSER-0.0.1.dist-info/WHEEL
code_secret_DARKSHLOSER-0.0.1.dist-info/top_level.txt
code_secret_DARKSHLOSER-0.0.1.dist-info/RECORD
