Metadata-Version: 2.1
Name: code-secret-DARKSHLOSER
Version: 0.0.1
Summary: Tool for securing sensitive code private/public repositories
Home-page: https://github.com/pypa/code-secret
Author: Dobromir Kovachev
Author-email: dobromir.mail@gmail.com
License: UNKNOWN
Platform: UNKNOWN
Classifier: Programming Language :: Python :: 3
Classifier: License :: OSI Approved :: MIT License
Classifier: Operating System :: OS Independent
Requires-Python: >=3.6
